{"title":"오디오클립 ─ 디지털투데이 매일듣는 디지털경제 뉴스 데일리픽","url":"https://audioclip.naver.com/channels/3508","favicon":"https://audioclip.naver.com/channels/favicon.ico","elements":[{"title":"[AI 아나운서] 애플, 9월 12일 아이폰15 공개...구글 만난 엔비디아, 주가 '최고치'","contents":"<span class=\"blind\">재생시간</span>8분","link":"https://audioclip.naver.com/channels/3508/clips/1018","retrieved":1693429723636,"image":"https://audio-phinf.pstatic.net/20230830_26/1693376307864fpPes_JPEG/%BF%C0%B5%F0%BF%C0%C5%AC%B8%B3%BD%E6%B3%D7%C0%CF_%BC%F6%C1%A4.jpg?type=f150_150"},{"title":"[AI 아나운서] 기업용 챗GPT 출격...엔비디아 GPU '빈부격차'","contents":"<span class=\"blind\">재생시간</span>8분","link":"https://audioclip.naver.com/channels/3508/clips/1017","retrieved":1693343250608,"image":"https://audio-phinf.pstatic.net/20230829_98/1693293983887qfEWf_JPEG/%BF%C0%B5%F0%BF%C0%C5%AC%B8%B3%BD%E6%B3%D7%C0%CF_%BC%F6%C1%A4.jpg?type=f150_150"},{"title":"[AI 아나운서] JP모건 \"암호화폐 상승장 머지않아\"...M3 아이패드 프로 특징은?","contents":"<span class=\"blind\">재생시간</span>8분","link":"https://audioclip.naver.com/channels/3508/clips/1016","retrieved":1693256859788,"image":"https://audio-phinf.pstatic.net/20230828_13/1693205613227NkewM_JPEG/%BF%C0%B5%F0%BF%C0%C5%AC%B8%B3%BD%E6%B3%D7%C0%CF_%BC%F6%C1%A4.jpg?type=f150_150"},{"title":"[AI 아나운서] 삼성-SK, HBM3 경쟁↑…中 경제 둔화 美 영향 '미비'","contents":"<span class=\"blind\">재생시간</span>6분","link":"https://audioclip.naver.com/channels/3508/clips/1015","retrieved":1693170408441,"image":"https://audio-phinf.pstatic.net/20230827_233/1693141588161AMcwa_JPEG/%BF%C0%B5%F0%BF%C0%C5%AC%B8%B3%BD%E6%B3%D7%C0%CF_%BC%F6%C1%A4.jpg?type=f150_150"},{"title":"[AI 아나운서] 애플, 비전 프로 2007년부터?...IBM, 뇌 신경망 닮은 AI 칩 개발","contents":"<span class=\"blind\">재생시간</span>7분","link":"https://audioclip.naver.com/channels/3508/clips/1014","retrieved":1692911273025},{"title":"[AI 아나운서] AI 칩 매출 534억달러 전망...美법무부, 바이낸스 수사 \"세탁 방치했다\"","contents":"<span class=\"blind\">재생시간</span>7분","link":"https://audioclip.naver.com/channels/3508/clips/1013","retrieved":1692824861018},{"title":"[AI 아나운서] 시스코, 엔비디아에 도전장?...IPO 대어 ARM \"가치 93조원\"","contents":"<span class=\"blind\">재생시간</span>8분","link":"https://audioclip.naver.com/channels/3508/clips/1012","retrieved":1692738471806},{"title":"[AI 아나운서] 비트코인 주간 수익률↓...러 달탐사 시도 '실패'","contents":"<span class=\"blind\">재생시간</span>8분","link":"https://audioclip.naver.com/channels/3508/clips/1011","retrieved":1692652075703},{"title":"[AI 아나운서] 삼성·LGD '올레도스' 개발 집중…유럽도 고금리 태풍","contents":"<span class=\"blind\">재생시간</span>6분","link":"https://audioclip.naver.com/channels/3508/clips/1010","retrieved":1692572842306},{"title":"[AI 아나운서] 중국발 경제 위기론 심상찮네...트럼프, 암호화폐 싫다더니?","contents":"<span class=\"blind\">재생시간</span>8분","link":"https://audioclip.naver.com/channels/3508/clips/1009","retrieved":1692306425590}]}